lanraragi_api/__init__.py
lanraragi_api/lanraragi.py
lanraragi_api/base/__init__.py
lanraragi_api/base/archive.py
lanraragi_api/base/base.py
lanraragi_api/base/category.py
lanraragi_api/base/database.py
lanraragi_api/base/minion.py
lanraragi_api/base/misc.py
lanraragi_api/base/search.py
lanraragi_api/base/shinobu.py
lanraragi_api/base/tankoubon.py
lanraragi_api/enhanced/__init__.py
lanraragi_api/enhanced/script.py
lanraragi_api/enhanced/server_side.py
lanraragi_api-0.9.60.2.dist-info/licenses/LICENSE
lanraragi_api-0.9.60.2.dist-info/METADATA
lanraragi_api-0.9.60.2.dist-info/WHEEL
lanraragi_api-0.9.60.2.dist-info/top_level.txt
lanraragi_api-0.9.60.2.dist-info/RECORD
