Metadata-Version: 2.4
Name: lanraragi_api
Version: 0.9.60.2
Summary: A Python library for LANraragi API.
Home-page: https://github.com/gustaavv/lanraragi-api
Author: Gustav
Author-email: gustaavv.git@yahoo.com
License-File: LICENSE
Requires-Dist: requests==2.32.5
Requires-Dist: pydantic==2.12.5
Dynamic: author
Dynamic: author-email
Dynamic: description
Dynamic: description-content-type
Dynamic: home-page
Dynamic: license-file
Dynamic: requires-dist
Dynamic: summary
